{
  "name": "tomkrieger-sshkeymgmt",
  "version": "1.1.0",
  "author": "Thomas Krieger",
  "summary": "Manage Unix users, groups and ssh keys",
  "license": "Apache-2.0",
  "source": "https://github.com/tom-krieger/sshkeymgmt.git",
  "project_page": "https://github.com/tom-krieger/sshkeymgmt",
  "issues_url": "https://github.com/tom-krieger/sshkeymgmt/issues",
  "dependencies": [
    {
      "name": "puppetlabs-stdlib",
      "version_requirement": ">= 4.6.0 < 10.0.0"
    },
    {
      "name": "puppetlabs-concat",
      "version_requirement": ">= 1.1.0 < 10.0.0"
    }
  ],
  "operatingsystem_support": [
    {
      "operatingsystem": "CentOS",
      "operatingsystemrelease": [
        "7",
        "8"
      ]
    },
    {
      "operatingsystem": "OracleLinux",
      "operatingsystemrelease": [
        "7",
        "8",
        "9"
      ]
    },
    {
      "operatingsystem": "RedHat",
      "operatingsystemrelease": [
        "7",
        "8",
        "9"
      ]
    },
    {
      "operatingsystem": "Scientific",
      "operatingsystemrelease": [
        "7"
      ]
    },
    {
      "operatingsystem": "Debian",
      "operatingsystemrelease": [
        "10",
        "11",
        "12"
      ]
    },
    {
      "operatingsystem": "Ubuntu",
      "operatingsystemrelease": [
        "18.04",
        "20.04",
        "22.04"
      ]
    },
    {
      "operatingsystem": "Fedora",
      "operatingsystemrelease": [
        "32",
        "34"
      ]
    },
    {
      "operatingsystem": "SLES",
      "operatingsystemrelease": [
        "12",
        "15"
      ]
    },
    {
      "operatingsystem": "Solaris",
      "operatingsystemrelease": [
        "11"
      ]
    }
  ],
  "requirements": [
    {
      "name": "puppet",
      "version_requirement": ">= 4.10.0 < 9.0.0"
    }
  ],
  "pdk-version": "2.7.1",
  "template-url": "pdk-default#2.7.4",
  "template-ref": "tags/2.7.4-0-g58edf57"
}
